rabbitmq_asynqp/__init__.py
rabbitmq_asynqp/consumer.py
rabbitmq_asynqp/messaging.py
rabbitmq_asynqp/producer.py
rabbitmq_asynqp/rabbitmq_consumer.py
rabbitmq_asynqp/rabbitmq_producer.py
rabbitmq_asynqp-0.1.1.data/scripts/example.py
rabbitmq_asynqp-0.1.1.dist-info/LICENSE
rabbitmq_asynqp-0.1.1.dist-info/METADATA
rabbitmq_asynqp-0.1.1.dist-info/WHEEL
rabbitmq_asynqp-0.1.1.dist-info/top_level.txt
rabbitmq_asynqp-0.1.1.dist-info/RECORD
