Metadata-Version: 2.1
Name: rabbitmq-asynqp
Version: 0.1.1
Summary: Implementation of rabbitmq with asynqp
Home-page: http://pypi.python.org/pypi/rabbitmq_asynqp/
Author: Akshay Agarwal
Author-email: akshay2agarwal@gmail.com
License: LICENSE.txt
Platform: UNKNOWN
Requires-Dist: asynqp (>=0.5.1)
